extract_pdf_highlighted_text.py
extract_pdf_highlighted_text-0.1.0a0.dist-info/licenses/LICENSE
extract_pdf_highlighted_text-0.1.0a0.dist-info/METADATA
extract_pdf_highlighted_text-0.1.0a0.dist-info/WHEEL
extract_pdf_highlighted_text-0.1.0a0.dist-info/top_level.txt
extract_pdf_highlighted_text-0.1.0a0.dist-info/RECORD
