Metadata-Version: 2.4
Name: extract-pdf-highlighted-text
Version: 0.1.0a0
Summary: Extract text that has been highlighted in PDF documents.
Author-email: Jifeng Wu <jifengwu2k@gmail.com>
License-Expression: MIT
Project-URL: Homepage, https://github.com/jifengwu2k/extract-pdf-highlighted-text
Project-URL: Bug Tracker, https://github.com/jifengwu2k/extract-pdf-highlighted-text/issues
Classifier: Programming Language :: Python :: 2
Classifier: Programming Language :: Python :: 3
Classifier: Operating System :: OS Independent
Requires-Python: >=2
License-File: LICENSE
Requires-Dist: PyPDF2
Requires-Dist: pdfminer.six
Requires-Dist: typing; python_version < "3.5"
Dynamic: license-file
